.README.rst.swp
.gitignore
.setup.py.swo
.setup.py.swp
.travis.yml
MANIFEST.in
README.rst
bootstrap.py
setup.py
travis.cfg
docs/.HISTORY.txt.swo
docs/.HISTORY.txt.swp
docs/CREDITS.txt
docs/HISTORY.txt
docs/INSTALL.txt
docs/LICENSE.GPL
docs/LICENSE.txt
hl/__init__.py
hl.plone.boardnotifications.egg-info/PKG-INFO
hl.plone.boardnotifications.egg-info/SOURCES.txt
hl.plone.boardnotifications.egg-info/dependency_links.txt
hl.plone.boardnotifications.egg-info/entry_points.txt
hl.plone.boardnotifications.egg-info/namespace_packages.txt
hl.plone.boardnotifications.egg-info/not-zip-safe
hl.plone.boardnotifications.egg-info/requires.txt
hl.plone.boardnotifications.egg-info/top_level.txt
hl/plone/__init__.py
hl/plone/boardnotifications/__init__.py
hl/plone/boardnotifications/configure.zcml
hl/plone/boardnotifications/eventhandlers.py
hl/plone/boardnotifications/interfaces.py
hl/plone/boardnotifications/notify.py
hl/plone/boardnotifications/rebuild_i18n.sh
hl/plone/boardnotifications/subscribe.py
hl/plone/boardnotifications/upgrades.py
hl/plone/boardnotifications/version.txt
hl/plone/boardnotifications/browser/__init__.py
hl/plone/boardnotifications/browser/configure.zcml
hl/plone/boardnotifications/browser/mailin.py
hl/plone/boardnotifications/browser/subscribe.pt
hl/plone/boardnotifications/browser/views.py
hl/plone/boardnotifications/locales/hl.plone.boardnotifications.pot
hl/plone/boardnotifications/locales/manual.pot
hl/plone/boardnotifications/locales/de/LC_MESSAGES/hl.plone.boardnotifications.mo
hl/plone/boardnotifications/locales/de/LC_MESSAGES/hl.plone.boardnotifications.po
hl/plone/boardnotifications/locales/en/LC_MESSAGES/hl.plone.boardnotifications.mo
hl/plone/boardnotifications/locales/en/LC_MESSAGES/hl.plone.boardnotifications.po
hl/plone/boardnotifications/locales/es/LC_MESSAGES/hl.plone.boardnotifications.mo
hl/plone/boardnotifications/locales/es/LC_MESSAGES/hl.plone.boardnotifications.po
hl/plone/boardnotifications/locales/eu/LC_MESSAGES/hl.plone.boardnotifications.mo
hl/plone/boardnotifications/locales/eu/LC_MESSAGES/hl.plone.boardnotifications.po
hl/plone/boardnotifications/profiles/default/componentregistry.xml
hl/plone/boardnotifications/profiles/default/controlpanel.xml
hl/plone/boardnotifications/profiles/default/memberdata_properties.xml
hl/plone/boardnotifications/profiles/default/metadata.xml
hl/plone/boardnotifications/tests/__init__.py
