Metadata-Version: 1.1
Name: hl.plone.boardnotifications
Version: 1.1
Summary: Notify users when Ploneboard threads or comments are modified
Home-page: https://github.com/Haufe-Lexware/hl.plone.boardnotifications
Author: see docs/CREDITS.txt
Author-email: t_schorr@gmx.de
License: GPL
Keywords: Plone Ploneboard board forum notifications
Platform: UNKNOWN
Classifier: Framework :: Plone
Classifier: Programming Language :: Python
